{
  "_fv": 13,
  "_type": "recipe",
  "definition": {
    "recipeType": "Crafting",
    "xpReward": 0.0,
    "cookingTime": 200,
    "recipeRetstackSize": 1,
    "group": "block_of_nether_soul_essence",
    "recipeShapeless": false,
    "recipeSlots": [
      {
        "value": "CUSTOM:NetherSoulEssence"
      },
      {
        "value": "CUSTOM:NetherSoulEssence"
      },
      {
        "value": "CUSTOM:NetherSoulEssence"
      },
      {
        "value": "CUSTOM:NetherSoulEssence"
      },
      {
        "value": "CUSTOM:NetherSoulEssence"
      },
      {
        "value": "CUSTOM:NetherSoulEssence"
      },
      {
        "value": "CUSTOM:NetherSoulEssence"
      },
      {
        "value": "CUSTOM:NetherSoulEssence"
      },
      {
        "value": "CUSTOM:NetherSoulEssence"
      }
    ],
    "recipeReturnStack": {
      "value": "CUSTOM:BlockofNetherSoulEssence"
    },
    "name": "block_of_nether_soul_essence_recipe",
    "namespace": "mod"
  }
}