{
  "_fv": 24,
  "_type": "recipe",
  "definition": {
    "recipeType": "Crafting",
    "xpReward": 0.0,
    "cookingTime": 200,
    "recipeRetstackSize": 8,
    "group": "horizontal_glass_bamboo",
    "recipeShapeless": false,
    "recipeSlots": [
      {
        "value": "Blocks.STAINED_GLASS_PANE#5"
      },
      {
        "value": "Blocks.STAINED_GLASS_PANE#5"
      },
      {
        "value": "Blocks.STAINED_GLASS_PANE#5"
      },
      {
        "value": "Blocks.STAINED_GLASS_PANE#5"
      },
      {
        "value": "CUSTOM:BambooBlock"
      },
      {
        "value": "Blocks.STAINED_GLASS_PANE#5"
      },
      {
        "value": "Blocks.STAINED_GLASS_PANE#5"
      },
      {
        "value": "Blocks.STAINED_GLASS_PANE#5"
      },
      {
        "value": "Blocks.STAINED_GLASS_PANE#5"
      }
    ],
    "recipeReturnStack": {
      "value": "CUSTOM:BambooFramedLimeStainedGlass"
    },
    "name": "fpr_bamboo_lime",
    "namespace": "mod"
  }
}