{
  "_fv": 13,
  "_type": "tag",
  "definition": {
    "type": "Items",
    "items": [
      {
        "value": "CUSTOM:HandmadeRevolver"
      },
      {
        "value": "CUSTOM:PepperBox"
      },
      {
        "value": "CUSTOM:ShortRevolver"
      },
      {
        "value": "CUSTOM:GoldenShotRevolver"
      },
      {
        "value": "CUSTOM:LongRevolver"
      },
      {
        "value": "CUSTOM:Lefs9"
      },
      {
        "value": "CUSTOM:EnhancedPepperBox"
      }
    ],
    "blocks": [],
    "functions": [],
    "name": "wobr_firearm_revolver",
    "namespace": "mod"
  }
}