{
  "group": "wooden_chiseled_group",
  "type": "minecraft:crafting_shaped",
  "pattern": [
    "012",
    "3 5",
    "678"
  ],
  "key": {
    "0": {
      "item": "byg:mahogany_log"
    },
    "1": {
      "item": "byg:mahogany_log"
    },
    "2": {
      "item": "byg:mahogany_log"
    },
    "3": {
      "item": "byg:mahogany_log"
    },
    "5": {
      "item": "byg:mahogany_log"
    },
    "6": {
      "item": "byg:mahogany_log"
    },
    "7": {
      "item": "byg:mahogany_log"
    },
    "8": {
      "item": "byg:mahogany_log"
    }
  },
  "result": {
    "item": "wobr:chiseled_byg_mahogany_wood",
    "count": 8
  }
}